[
  {
    "text": "bvba",
    "size": 122
  },
  {
    "text": "ferme",
    "size": 92
  },
  {
    "text": "lv",
    "size": 78
  },
  {
    "text": "luc",
    "size": 52
  },
  {
    "text": "nv",
    "size": 45
  },
  {
    "text": "johan",
    "size": 41
  },
  {
    "text": "agri",
    "size": 40
  },
  {
    "text": "tuinen",
    "size": 39
  },
  {
    "text": "bart",
    "size": 38
  },
  {
    "text": "den",
    "size": 32
  },
  {
    "text": "marc",
    "size": 32
  },
  {
    "text": "geert",
    "size": 31
  },
  {
    "text": "sprl",
    "size": 29
  },
  {
    "text": "jardins",
    "size": 28
  },
  {
    "text": "wim",
    "size": 26
  },
  {
    "text": "jardin",
    "size": 24
  },
  {
    "text": "fruit",
    "size": 24
  },
  {
    "text": "agro",
    "size": 23
  },
  {
    "text": "dirk",
    "size": 23
  },
  {
    "text": "patrick",
    "size": 21
  },
  {
    "text": "kristof",
    "size": 18
  },
  {
    "text": "david",
    "size": 18
  },
  {
    "text": "peter",
    "size": 18
  },
  {
    "text": "tom",
    "size": 17
  },
  {
    "text": "bernard",
    "size": 17
  },
  {
    "text": "philippe",
    "size": 17
  },
  {
    "text": "pieter",
    "size": 17
  },
  {
    "text": "jan",
    "size": 17
  },
  {
    "text": "sagr",
    "size": 17
  },
  {
    "text": "green",
    "size": 16
  },
  {
    "text": "koen",
    "size": 16
  },
  {
    "text": "bert",
    "size": 16
  },
  {
    "text": "olivier",
    "size": 16
  },
  {
    "text": "kris",
    "size": 16
  },
  {
    "text": "nicolas",
    "size": 15
  },
  {
    "text": "garden",
    "size": 15
  },
  {
    "text": "entreprise",
    "size": 15
  },
  {
    "text": "joseph",
    "size": 14
  },
  {
    "text": "stefaan",
    "size": 14
  },
  {
    "text": "gebroeders",
    "size": 14
  },
  {
    "text": "christophe",
    "size": 14
  },
  {
    "text": "eric",
    "size": 13
  },
  {
    "text": "fv",
    "size": 13
  },
  {
    "text": "hof",
    "size": 13
  },
  {
    "text": "vanneste",
    "size": 13
  },
  {
    "text": "filip",
    "size": 13
  },
  {
    "text": "pierre",
    "size": 12
  },
  {
    "text": "steven",
    "size": 12
  },
  {
    "text": "willy",
    "size": 12
  },
  {
    "text": "michel",
    "size": 12
  },
  {
    "text": "christine",
    "size": 12
  },
  {
    "text": "groenten",
    "size": 12
  },
  {
    "text": "hans",
    "size": 11
  },
  {
    "text": "jozef",
    "size": 11
  },
  {
    "text": "dominique",
    "size": 11
  },
  {
    "text": "tuinaanleg",
    "size": 11
  },
  {
    "text": "agricole",
    "size": 11
  },
  {
    "text": "tuinbouwbedrijf",
    "size": 11
  },
  {
    "text": "joris",
    "size": 11
  },
  {
    "text": "legrand",
    "size": 11
  },
  {
    "text": "danny",
    "size": 11
  },
  {
    "text": "jean",
    "size": 11
  },
  {
    "text": "vincent",
    "size": 11
  },
  {
    "text": "paul",
    "size": 10
  },
  {
    "text": "maes",
    "size": 10
  },
  {
    "text": "yves",
    "size": 10
  },
  {
    "text": "pascal",
    "size": 10
  },
  {
    "text": "françois",
    "size": 10
  },
  {
    "text": "tuin",
    "size": 10
  },
  {
    "text": "ter",
    "size": 9
  },
  {
    "text": "mathieu",
    "size": 9
  },
  {
    "text": "thomas",
    "size": 9
  },
  {
    "text": "francis",
    "size": 9
  },
  {
    "text": "champignons",
    "size": 9
  },
  {
    "text": "consulting",
    "size": 9
  },
  {
    "text": "fils",
    "size": 9
  },
  {
    "text": "farm",
    "size": 9
  },
  {
    "text": "rik",
    "size": 9
  },
  {
    "text": "boomkwekerij",
    "size": 9
  },
  {
    "text": "bio",
    "size": 9
  },
  {
    "text": "didier",
    "size": 9
  },
  {
    "text": "freddy",
    "size": 8
  },
  {
    "text": "louis",
    "size": 8
  },
  {
    "text": "stijn",
    "size": 8
  },
  {
    "text": "herman",
    "size": 8
  },
  {
    "text": "andré",
    "size": 8
  },
  {
    "text": "andre",
    "size": 8
  },
  {
    "text": "frank",
    "size": 8
  },
  {
    "text": "daniel",
    "size": 8
  },
  {
    "text": "frederik",
    "size": 8
  },
  {
    "text": "service",
    "size": 8
  },
  {
    "text": "guy",
    "size": 8
  },
  {
    "text": "dries",
    "size": 8
  },
  {
    "text": "marie",
    "size": 8
  },
  {
    "text": "maria",
    "size": 8
  },
  {
    "text": "plants",
    "size": 8
  },
  {
    "text": "nico",
    "size": 8
  },
  {
    "text": "saveurs",
    "size": 8
  },
  {
    "text": "peeters",
    "size": 8
  },
  {
    "text": "ghislain",
    "size": 8
  },
  {
    "text": "alain",
    "size": 8
  },
  {
    "text": "guido",
    "size": 8
  },
  {
    "text": "wouters",
    "size": 7
  },
  {
    "text": "cornette",
    "size": 7
  },
  {
    "text": "zoon",
    "size": 7
  },
  {
    "text": "karel",
    "size": 7
  },
  {
    "text": "lieven",
    "size": 7
  },
  {
    "text": "kurt",
    "size": 7
  },
  {
    "text": "belgium",
    "size": 7
  },
  {
    "text": "ets",
    "size": 7
  },
  {
    "text": "sébastien",
    "size": 7
  },
  {
    "text": "haghedooren",
    "size": 7
  },
  {
    "text": "co",
    "size": 7
  },
  {
    "text": "bloemen",
    "size": 7
  },
  {
    "text": "vert",
    "size": 7
  },
  {
    "text": "eddy",
    "size": 7
  },
  {
    "text": "thierry",
    "size": 7
  },
  {
    "text": "potager",
    "size": 7
  },
  {
    "text": "laurent",
    "size": 7
  },
  {
    "text": "gilles",
    "size": 7
  },
  {
    "text": "bloemisterij",
    "size": 7
  },
  {
    "text": "christian",
    "size": 7
  },
  {
    "text": "simon",
    "size": 7
  },
  {
    "text": "emmanuel",
    "size": 7
  },
  {
    "text": "jonckheere",
    "size": 7
  },
  {
    "text": "gert",
    "size": 7
  },
  {
    "text": "frédéric",
    "size": 7
  },
  {
    "text": "plant",
    "size": 7
  },
  {
    "text": "horticulture",
    "size": 7
  },
  {
    "text": "fresh",
    "size": 7
  },
  {
    "text": "landbouwwerken",
    "size": 7
  },
  {
    "text": "nature",
    "size": 7
  },
  {
    "text": "marnix",
    "size": 6
  },
  {
    "text": "cie",
    "size": 6
  },
  {
    "text": "hendrik",
    "size": 6
  },
  {
    "text": "ivan",
    "size": 6
  },
  {
    "text": "services",
    "size": 6
  },
  {
    "text": "erik",
    "size": 6
  },
  {
    "text": "wouter",
    "size": 6
  },
  {
    "text": "nederlands",
    "size": 6
  },
  {
    "text": "devos",
    "size": 6
  },
  {
    "text": "tuincentrum",
    "size": 6
  },
  {
    "text": "jacques",
    "size": 6
  },
  {
    "text": "ver",
    "size": 6
  },
  {
    "text": "els",
    "size": 6
  },
  {
    "text": "marcel",
    "size": 6
  },
  {
    "text": "martin",
    "size": 6
  },
  {
    "text": "etienne",
    "size": 6
  },
  {
    "text": "janssens",
    "size": 6
  },
  {
    "text": "rita",
    "size": 6
  },
  {
    "text": "groene",
    "size": 6
  },
  {
    "text": "spriet",
    "size": 6
  },
  {
    "text": "benoit",
    "size": 6
  },
  {
    "text": "jeroen",
    "size": 6
  },
  {
    "text": "cédric",
    "size": 6
  },
  {
    "text": "hoeve",
    "size": 6
  },
  {
    "text": "frederic",
    "size": 6
  },
  {
    "text": "pauwels",
    "size": 6
  },
  {
    "text": "davy",
    "size": 6
  },
  {
    "text": "chris",
    "size": 6
  },
  {
    "text": "vermeulen",
    "size": 6
  },
  {
    "text": "martens",
    "size": 6
  },
  {
    "text": "nijs",
    "size": 6
  },
  {
    "text": "benjamin",
    "size": 6
  },
  {
    "text": "dendauw",
    "size": 6
  },
  {
    "text": "danneels",
    "size": 6
  },
  {
    "text": "onderhoud",
    "size": 6
  },
  {
    "text": "projects",
    "size": 6
  },
  {
    "text": "freres",
    "size": 6
  },
  {
    "text": "callewaert",
    "size": 6
  },
  {
    "text": "francois",
    "size": 6
  },
  {
    "text": "parcs",
    "size": 6
  },
  {
    "text": "xavier",
    "size": 6
  },
  {
    "text": "ten",
    "size": 5
  },
  {
    "text": "tim",
    "size": 5
  },
  {
    "text": "algemene",
    "size": 5
  },
  {
    "text": "wauters",
    "size": 5
  },
  {
    "text": "consult",
    "size": 5
  },
  {
    "text": "denis",
    "size": 5
  },
  {
    "text": "f.v",
    "size": 5
  },
  {
    "text": "baes",
    "size": 5
  },
  {
    "text": "julien",
    "size": 5
  },
  {
    "text": "trading",
    "size": 5
  },
  {
    "text": "stéphane",
    "size": 5
  },
  {
    "text": "moens",
    "size": 5
  },
  {
    "text": "association",
    "size": 5
  },
  {
    "text": "wilfried",
    "size": 5
  },
  {
    "text": "jans",
    "size": 5
  },
  {
    "text": "jurgen",
    "size": 5
  },
  {
    "text": "urban",
    "size": 5
  },
  {
    "text": "kwekerij",
    "size": 5
  },
  {
    "text": "frans",
    "size": 5
  },
  {
    "text": "smet",
    "size": 5
  },
  {
    "text": "vandamme",
    "size": 5
  },
  {
    "text": "dany",
    "size": 5
  },
  {
    "text": "vande",
    "size": 5
  },
  {
    "text": "jean-françois",
    "size": 5
  },
  {
    "text": "groen",
    "size": 5
  },
  {
    "text": "roland",
    "size": 5
  },
  {
    "text": "etablissements",
    "size": 5
  },
  {
    "text": "goossens",
    "size": 5
  },
  {
    "text": "mario",
    "size": 5
  },
  {
    "text": "entreprises",
    "size": 5
  },
  {
    "text": "grondwerken",
    "size": 5
  },
  {
    "text": "benny",
    "size": 5
  },
  {
    "text": "antoine",
    "size": 5
  },
  {
    "text": "verhelst",
    "size": 5
  },
  {
    "text": "jens",
    "size": 5
  },
  {
    "text": "tuinwerken",
    "size": 5
  },
  {
    "text": "damien",
    "size": 5
  },
  {
    "text": "hulle",
    "size": 5
  },
  {
    "text": "monique",
    "size": 5
  },
  {
    "text": "adam",
    "size": 5
  },
  {
    "text": "pauwelyn",
    "size": 5
  },
  {
    "text": "roger",
    "size": 5
  },
  {
    "text": "piet",
    "size": 4
  },
  {
    "text": "verstraete",
    "size": 4
  },
  {
    "text": "andy",
    "size": 4
  },
  {
    "text": "depoorter",
    "size": 4
  },
  {
    "text": "anne",
    "size": 4
  },
  {
    "text": "loonwerken",
    "size": 4
  },
  {
    "text": "vromman",
    "size": 4
  },
  {
    "text": "stragier",
    "size": 4
  },
  {
    "text": "desmedt",
    "size": 4
  },
  {
    "text": "casier",
    "size": 4
  },
  {
    "text": "looveren",
    "size": 4
  },
  {
    "text": "veehandel",
    "size": 4
  },
  {
    "text": "dupont",
    "size": 4
  },
  {
    "text": "dijck",
    "size": 4
  },
  {
    "text": "invest",
    "size": 4
  },
  {
    "text": "atelier",
    "size": 4
  },
  {
    "text": "mol",
    "size": 4
  },
  {
    "text": "landbouwbedrijf",
    "size": 4
  },
  {
    "text": "galle",
    "size": 4
  },
  {
    "text": "janssen",
    "size": 4
  },
  {
    "text": "huis",
    "size": 4
  },
  {
    "text": "martine",
    "size": 4
  },
  {
    "text": "herdt",
    "size": 4
  },
  {
    "text": "cv",
    "size": 4
  },
  {
    "text": "dillen",
    "size": 4
  },
  {
    "text": "huys",
    "size": 4
  },
  {
    "text": "management",
    "size": 4
  },
  {
    "text": "jo",
    "size": 4
  },
  {
    "text": "henk",
    "size": 4
  },
  {
    "text": "verger",
    "size": 4
  },
  {
    "text": "pepiniere",
    "size": 4
  },
  {
    "text": "société",
    "size": 4
  },
  {
    "text": "ronny",
    "size": 4
  },
  {
    "text": "viaene",
    "size": 4
  },
  {
    "text": "gilbert",
    "size": 4
  }
]