[
  {
    "form": "Natuurlijk Persoon",
    "count": 861
  },
  {
    "form": "Besloten vennootschap met beperkte aansprakelijkheid",
    "count": 239
  },
  {
    "form": "Buitenlandse onderneming",
    "count": 3
  },
  {
    "form": "Coöperatieve vennootschap (oud statuut)",
    "count": 1
  },
  {
    "form": "Coöperatieve vennootschap met beperkte aansprakelijkheid",
    "count": 3
  },
  {
    "form": "Coöperatieve vennootschap met beperkte aansprakelijkheid met een sociaal oogmerk",
    "count": 1
  },
  {
    "form": "Coöperatieve vennootschap met onbeperkte aansprakelijkheid",
    "count": 2
  },
  {
    "form": "Eenpersoons besloten vennootschap met beperkte aansprakelijkheid",
    "count": 8
  },
  {
    "form": "Gewone commanditaire vennootschap",
    "count": 18
  },
  {
    "form": "Naamloze vennootschap",
    "count": 63
  },
  {
    "form": "Vennootschap of vereniging zonder rechtspersoonlijkheid",
    "count": 3
  },
  {
    "form": "Vennootschap onder firma",
    "count": 16
  },
  {
    "form": "Vereniging zonder winstoogmerk",
    "count": 9
  }
]