[
  {
    "text": "bvba",
    "size": 411
  },
  {
    "text": "interieur",
    "size": 351
  },
  {
    "text": "design",
    "size": 238
  },
  {
    "text": "menuiserie",
    "size": 202
  },
  {
    "text": "construct",
    "size": 201
  },
  {
    "text": "schrijnwerkerij",
    "size": 166
  },
  {
    "text": "nv",
    "size": 156
  },
  {
    "text": "sprl",
    "size": 145
  },
  {
    "text": "algemene",
    "size": 138
  },
  {
    "text": "concept",
    "size": 121
  },
  {
    "text": "atelier",
    "size": 109
  },
  {
    "text": "projects",
    "size": 109
  },
  {
    "text": "keukens",
    "size": 105
  },
  {
    "text": "bart",
    "size": 93
  },
  {
    "text": "wood",
    "size": 90
  },
  {
    "text": "tom",
    "size": 82
  },
  {
    "text": "marc",
    "size": 80
  },
  {
    "text": "peter",
    "size": 79
  },
  {
    "text": "den",
    "size": 77
  },
  {
    "text": "luc",
    "size": 77
  },
  {
    "text": "bois",
    "size": 75
  },
  {
    "text": "services",
    "size": 73
  },
  {
    "text": "jan",
    "size": 67
  },
  {
    "text": "johan",
    "size": 64
  },
  {
    "text": "patrick",
    "size": 63
  },
  {
    "text": "wim",
    "size": 62
  },
  {
    "text": "home",
    "size": 62
  },
  {
    "text": "co",
    "size": 61
  },
  {
    "text": "koen",
    "size": 61
  },
  {
    "text": "david",
    "size": 58
  },
  {
    "text": "dirk",
    "size": 57
  },
  {
    "text": "service",
    "size": 55
  },
  {
    "text": "schrijnwerk",
    "size": 52
  },
  {
    "text": "steven",
    "size": 51
  },
  {
    "text": "schrijnwerken",
    "size": 50
  },
  {
    "text": "klussenier",
    "size": 49
  },
  {
    "text": "kristof",
    "size": 48
  },
  {
    "text": "decor",
    "size": 48
  },
  {
    "text": "philippe",
    "size": 48
  },
  {
    "text": "geert",
    "size": 48
  },
  {
    "text": "interior",
    "size": 47
  },
  {
    "text": "the",
    "size": 47
  },
  {
    "text": "art",
    "size": 47
  },
  {
    "text": "solutions",
    "size": 46
  },
  {
    "text": "dakwerken",
    "size": 46
  },
  {
    "text": "studio",
    "size": 46
  },
  {
    "text": "bouw",
    "size": 44
  },
  {
    "text": "thomas",
    "size": 43
  },
  {
    "text": "christophe",
    "size": 43
  },
  {
    "text": "stijn",
    "size": 43
  },
  {
    "text": "deco",
    "size": 43
  },
  {
    "text": "kris",
    "size": 41
  },
  {
    "text": "renovatie",
    "size": 40
  },
  {
    "text": "bouwwerken",
    "size": 40
  },
  {
    "text": "meubelen",
    "size": 38
  },
  {
    "text": "construction",
    "size": 37
  },
  {
    "text": "all",
    "size": 37
  },
  {
    "text": "eric",
    "size": 36
  },
  {
    "text": "kurt",
    "size": 36
  },
  {
    "text": "technics",
    "size": 35
  },
  {
    "text": "guy",
    "size": 35
  },
  {
    "text": "timmerwerken",
    "size": 35
  },
  {
    "text": "pieter",
    "size": 34
  },
  {
    "text": "bert",
    "size": 33
  },
  {
    "text": "davy",
    "size": 33
  },
  {
    "text": "and",
    "size": 33
  },
  {
    "text": "ets",
    "size": 32
  },
  {
    "text": "interieurbouw",
    "size": 32
  },
  {
    "text": "sven",
    "size": 32
  },
  {
    "text": "schilderwerken",
    "size": 32
  },
  {
    "text": "interiors",
    "size": 32
  },
  {
    "text": "pascal",
    "size": 32
  },
  {
    "text": "olivier",
    "size": 32
  },
  {
    "text": "maatwerk",
    "size": 31
  },
  {
    "text": "timmer",
    "size": 31
  },
  {
    "text": "entreprise",
    "size": 31
  },
  {
    "text": "hout",
    "size": 31
  },
  {
    "text": "tuinen",
    "size": 30
  },
  {
    "text": "bruno",
    "size": 30
  },
  {
    "text": "project",
    "size": 30
  },
  {
    "text": "frank",
    "size": 30
  },
  {
    "text": "filip",
    "size": 30
  },
  {
    "text": "paul",
    "size": 30
  },
  {
    "text": "alain",
    "size": 30
  },
  {
    "text": "erik",
    "size": 29
  },
  {
    "text": "maison",
    "size": 29
  },
  {
    "text": "yves",
    "size": 29
  },
  {
    "text": "michel",
    "size": 29
  },
  {
    "text": "fils",
    "size": 29
  },
  {
    "text": "kevin",
    "size": 28
  },
  {
    "text": "janssens",
    "size": 28
  },
  {
    "text": "tim",
    "size": 28
  },
  {
    "text": "danny",
    "size": 28
  },
  {
    "text": "belgium",
    "size": 27
  },
  {
    "text": "thierry",
    "size": 27
  },
  {
    "text": "nico",
    "size": 27
  },
  {
    "text": "daniel",
    "size": 27
  },
  {
    "text": "invest",
    "size": 26
  },
  {
    "text": "ebenisterie",
    "size": 26
  },
  {
    "text": "creations",
    "size": 26
  },
  {
    "text": "group",
    "size": 26
  },
  {
    "text": "maes",
    "size": 25
  },
  {
    "text": "chris",
    "size": 25
  },
  {
    "text": "laurent",
    "size": 25
  },
  {
    "text": "jonas",
    "size": 25
  },
  {
    "text": "renovatiewerken",
    "size": 24
  },
  {
    "text": "works",
    "size": 24
  },
  {
    "text": "house",
    "size": 24
  },
  {
    "text": "vincent",
    "size": 24
  },
  {
    "text": "stefaan",
    "size": 24
  },
  {
    "text": "eddy",
    "size": 24
  },
  {
    "text": "concepts",
    "size": 23
  },
  {
    "text": "international",
    "size": 23
  },
  {
    "text": "interieurs",
    "size": 23
  },
  {
    "text": "andy",
    "size": 23
  },
  {
    "text": "dieter",
    "size": 23
  },
  {
    "text": "smet",
    "size": 23
  },
  {
    "text": "jacobs",
    "size": 23
  },
  {
    "text": "dries",
    "size": 22
  },
  {
    "text": "jean",
    "size": 22
  },
  {
    "text": "peeters",
    "size": 22
  },
  {
    "text": "pierre",
    "size": 22
  },
  {
    "text": "electro",
    "size": 22
  },
  {
    "text": "steve",
    "size": 22
  },
  {
    "text": "gert",
    "size": 22
  },
  {
    "text": "furniture",
    "size": 21
  },
  {
    "text": "constructions",
    "size": 21
  },
  {
    "text": "ramen",
    "size": 21
  },
  {
    "text": "werken",
    "size": 21
  },
  {
    "text": "willems",
    "size": 21
  },
  {
    "text": "garden",
    "size": 21
  },
  {
    "text": "wouter",
    "size": 20
  },
  {
    "text": "company",
    "size": 20
  },
  {
    "text": "ronny",
    "size": 20
  },
  {
    "text": "klusjesdienst",
    "size": 20
  },
  {
    "text": "nick",
    "size": 20
  },
  {
    "text": "style",
    "size": 20
  },
  {
    "text": "stefan",
    "size": 20
  },
  {
    "text": "cuisines",
    "size": 20
  },
  {
    "text": "hans",
    "size": 20
  },
  {
    "text": "consulting",
    "size": 20
  },
  {
    "text": "jo",
    "size": 19
  },
  {
    "text": "plus",
    "size": 19
  },
  {
    "text": "l\u0027atelier",
    "size": 19
  },
  {
    "text": "dimitri",
    "size": 19
  },
  {
    "text": "martens",
    "size": 19
  },
  {
    "text": "joris",
    "size": 19
  },
  {
    "text": "pauwels",
    "size": 18
  },
  {
    "text": "claes",
    "size": 18
  },
  {
    "text": "frederik",
    "size": 18
  },
  {
    "text": "denis",
    "size": 18
  },
  {
    "text": "vof",
    "size": 18
  },
  {
    "text": "sébastien",
    "size": 18
  },
  {
    "text": "deuren",
    "size": 18
  },
  {
    "text": "creation",
    "size": 17
  },
  {
    "text": "rudi",
    "size": 17
  },
  {
    "text": "pro",
    "size": 17
  },
  {
    "text": "building",
    "size": 17
  },
  {
    "text": "frédéric",
    "size": 17
  },
  {
    "text": "sam",
    "size": 17
  },
  {
    "text": "mario",
    "size": 17
  },
  {
    "text": "parket",
    "size": 17
  },
  {
    "text": "jurgen",
    "size": 17
  },
  {
    "text": "simon",
    "size": 17
  },
  {
    "text": "didier",
    "size": 17
  },
  {
    "text": "martin",
    "size": 16
  },
  {
    "text": "cv",
    "size": 16
  },
  {
    "text": "nicolas",
    "size": 16
  },
  {
    "text": "christian",
    "size": 16
  },
  {
    "text": "zoon",
    "size": 16
  },
  {
    "text": "meubles",
    "size": 16
  },
  {
    "text": "schrijn",
    "size": 16
  },
  {
    "text": "gilles",
    "size": 16
  },
  {
    "text": "rik",
    "size": 16
  },
  {
    "text": "team",
    "size": 16
  },
  {
    "text": "jeroen",
    "size": 16
  },
  {
    "text": "reno",
    "size": 16
  },
  {
    "text": "algemeen",
    "size": 16
  },
  {
    "text": "karweiwerken",
    "size": 16
  },
  {
    "text": "cleaning",
    "size": 16
  },
  {
    "text": "huis",
    "size": 15
  },
  {
    "text": "rudy",
    "size": 15
  },
  {
    "text": "meubelmakerij",
    "size": 15
  },
  {
    "text": "metal",
    "size": 15
  },
  {
    "text": "bram",
    "size": 15
  },
  {
    "text": "dominique",
    "size": 15
  },
  {
    "text": "gebroeders",
    "size": 15
  },
  {
    "text": "interieurinrichting",
    "size": 15
  },
  {
    "text": "mertens",
    "size": 15
  },
  {
    "text": "niels",
    "size": 15
  },
  {
    "text": "bernard",
    "size": 15
  },
  {
    "text": "maarten",
    "size": 15
  },
  {
    "text": "xavier",
    "size": 15
  },
  {
    "text": "maat",
    "size": 14
  },
  {
    "text": "gregory",
    "size": 14
  },
  {
    "text": "lieven",
    "size": 14
  },
  {
    "text": "renov",
    "size": 14
  },
  {
    "text": "renovation",
    "size": 14
  },
  {
    "text": "meubel",
    "size": 14
  },
  {
    "text": "jos",
    "size": 14
  },
  {
    "text": "renovaties",
    "size": 14
  },
  {
    "text": "laswerken",
    "size": 14
  },
  {
    "text": "new",
    "size": 14
  },
  {
    "text": "gunther",
    "size": 14
  },
  {
    "text": "wesley",
    "size": 14
  },
  {
    "text": "alex",
    "size": 14
  },
  {
    "text": "françois",
    "size": 14
  },
  {
    "text": "green",
    "size": 14
  },
  {
    "text": "willy",
    "size": 14
  },
  {
    "text": "benoit",
    "size": 14
  },
  {
    "text": "michael",
    "size": 14
  },
  {
    "text": "interieurwerken",
    "size": 14
  },
  {
    "text": "john",
    "size": 14
  },
  {
    "text": "immo",
    "size": 14
  },
  {
    "text": "jozef",
    "size": 13
  },
  {
    "text": "kitchen",
    "size": 13
  },
  {
    "text": "vanden",
    "size": 13
  },
  {
    "text": "julien",
    "size": 13
  },
  {
    "text": "decoratie",
    "size": 13
  },
  {
    "text": "clean",
    "size": 13
  },
  {
    "text": "serge",
    "size": 13
  },
  {
    "text": "montage",
    "size": 13
  },
  {
    "text": "guido",
    "size": 13
  },
  {
    "text": "michaël",
    "size": 13
  },
  {
    "text": "mathieu",
    "size": 13
  },
  {
    "text": "kenny",
    "size": 13
  },
  {
    "text": "schreinerei",
    "size": 13
  },
  {
    "text": "quality",
    "size": 13
  },
  {
    "text": "dave",
    "size": 13
  },
  {
    "text": "dak",
    "size": 12
  },
  {
    "text": "trading",
    "size": 12
  },
  {
    "text": "eco",
    "size": 12
  },
  {
    "text": "herman",
    "size": 12
  },
  {
    "text": "at",
    "size": 12
  },
  {
    "text": "lemmens",
    "size": 12
  },
  {
    "text": "gcv",
    "size": 12
  },
  {
    "text": "products",
    "size": 12
  },
  {
    "text": "decoratiewerken",
    "size": 12
  },
  {
    "text": "werner",
    "size": 12
  },
  {
    "text": "karel",
    "size": 12
  },
  {
    "text": "louis",
    "size": 12
  },
  {
    "text": "francis",
    "size": 12
  },
  {
    "text": "euro",
    "size": 12
  },
  {
    "text": "houtbewerking",
    "size": 12
  },
  {
    "text": "segers",
    "size": 12
  },
  {
    "text": "klus",
    "size": 12
  },
  {
    "text": "bouwonderneming",
    "size": 12
  },
  {
    "text": "total",
    "size": 12
  },
  {
    "text": "devos",
    "size": 12
  },
  {
    "text": "inox",
    "size": 12
  }
]