[
  {
    "text": "services",
    "size": 39
  },
  {
    "text": "service",
    "size": 32
  },
  {
    "text": "bvba",
    "size": 29
  },
  {
    "text": "technics",
    "size": 28
  },
  {
    "text": "belgium",
    "size": 27
  },
  {
    "text": "solutions",
    "size": 19
  },
  {
    "text": "consulting",
    "size": 17
  },
  {
    "text": "engineering",
    "size": 14
  },
  {
    "text": "maintenance",
    "size": 12
  },
  {
    "text": "projects",
    "size": 10
  },
  {
    "text": "and",
    "size": 9
  },
  {
    "text": "europe",
    "size": 8
  },
  {
    "text": "luc",
    "size": 7
  },
  {
    "text": "electronics",
    "size": 7
  },
  {
    "text": "repair",
    "size": 7
  },
  {
    "text": "systems",
    "size": 7
  },
  {
    "text": "benelux",
    "size": 7
  },
  {
    "text": "center",
    "size": 6
  },
  {
    "text": "group",
    "size": 6
  },
  {
    "text": "company",
    "size": 6
  },
  {
    "text": "construct",
    "size": 6
  },
  {
    "text": "industry",
    "size": 6
  },
  {
    "text": "vof",
    "size": 6
  },
  {
    "text": "sprl",
    "size": 6
  },
  {
    "text": "nv",
    "size": 6
  },
  {
    "text": "garage",
    "size": 6
  },
  {
    "text": "sven",
    "size": 6
  },
  {
    "text": "the",
    "size": 5
  },
  {
    "text": "geert",
    "size": 5
  },
  {
    "text": "kevin",
    "size": 5
  },
  {
    "text": "project",
    "size": 5
  },
  {
    "text": "marc",
    "size": 5
  },
  {
    "text": "jan",
    "size": 5
  },
  {
    "text": "bernard",
    "size": 5
  },
  {
    "text": "care",
    "size": 5
  },
  {
    "text": "onderhoud",
    "size": 5
  },
  {
    "text": "wim",
    "size": 5
  },
  {
    "text": "alain",
    "size": 5
  },
  {
    "text": "kris",
    "size": 5
  },
  {
    "text": "auto",
    "size": 5
  },
  {
    "text": "energy",
    "size": 4
  },
  {
    "text": "techniek",
    "size": 4
  },
  {
    "text": "tom",
    "size": 4
  },
  {
    "text": "tech",
    "size": 4
  },
  {
    "text": "eric",
    "size": 4
  },
  {
    "text": "concept",
    "size": 4
  },
  {
    "text": "brecht",
    "size": 4
  },
  {
    "text": "den",
    "size": 4
  },
  {
    "text": "flemalle",
    "size": 4
  },
  {
    "text": "thomas",
    "size": 4
  },
  {
    "text": "solution",
    "size": 4
  },
  {
    "text": "cegelec",
    "size": 4
  },
  {
    "text": "bart",
    "size": 4
  },
  {
    "text": "technical",
    "size": 4
  },
  {
    "text": "transport",
    "size": 4
  },
  {
    "text": "frédéric",
    "size": 4
  },
  {
    "text": "entreprise",
    "size": 4
  },
  {
    "text": "olivier",
    "size": 4
  },
  {
    "text": "stefaan",
    "size": 4
  },
  {
    "text": "electro",
    "size": 3
  },
  {
    "text": "mobile",
    "size": 3
  },
  {
    "text": "koen",
    "size": 3
  },
  {
    "text": "industries",
    "size": 3
  },
  {
    "text": "automation",
    "size": 3
  },
  {
    "text": "laurent",
    "size": 3
  },
  {
    "text": "algemene",
    "size": 3
  },
  {
    "text": "industrial",
    "size": 3
  },
  {
    "text": "kristof",
    "size": 3
  },
  {
    "text": "medical",
    "size": 3
  },
  {
    "text": "bram",
    "size": 3
  },
  {
    "text": "business",
    "size": 3
  },
  {
    "text": "michael",
    "size": 3
  },
  {
    "text": "equipment",
    "size": 3
  },
  {
    "text": "rudi",
    "size": 3
  },
  {
    "text": "atelier",
    "size": 3
  },
  {
    "text": "vdb",
    "size": 3
  },
  {
    "text": "klus",
    "size": 3
  },
  {
    "text": "yves",
    "size": 3
  },
  {
    "text": "marcke",
    "size": 3
  },
  {
    "text": "martin",
    "size": 3
  },
  {
    "text": "shop",
    "size": 3
  },
  {
    "text": "dieter",
    "size": 3
  },
  {
    "text": "eeckhout",
    "size": 3
  },
  {
    "text": "elec",
    "size": 3
  },
  {
    "text": "electric",
    "size": 3
  },
  {
    "text": "co",
    "size": 3
  },
  {
    "text": "heating",
    "size": 3
  },
  {
    "text": "consultancy",
    "size": 3
  },
  {
    "text": "dirk",
    "size": 3
  },
  {
    "text": "plus",
    "size": 3
  },
  {
    "text": "technic",
    "size": 3
  },
  {
    "text": "electrics",
    "size": 3
  },
  {
    "text": "support",
    "size": 3
  },
  {
    "text": "norman",
    "size": 3
  },
  {
    "text": "tools",
    "size": 3
  },
  {
    "text": "development",
    "size": 3
  },
  {
    "text": "security",
    "size": 3
  },
  {
    "text": "welding",
    "size": 2
  },
  {
    "text": "davy",
    "size": 2
  },
  {
    "text": "glenn",
    "size": 2
  },
  {
    "text": "vande",
    "size": 2
  },
  {
    "text": "hans",
    "size": 2
  },
  {
    "text": "cuyvers",
    "size": 2
  },
  {
    "text": "blue",
    "size": 2
  },
  {
    "text": "geusens",
    "size": 2
  },
  {
    "text": "patrick",
    "size": 2
  },
  {
    "text": "société",
    "size": 2
  },
  {
    "text": "with",
    "size": 2
  },
  {
    "text": "jozef",
    "size": 2
  },
  {
    "text": "groep",
    "size": 2
  },
  {
    "text": "andy",
    "size": 2
  },
  {
    "text": "machines",
    "size": 2
  },
  {
    "text": "antwerpen",
    "size": 2
  },
  {
    "text": "dries",
    "size": 2
  },
  {
    "text": "ppa",
    "size": 2
  },
  {
    "text": "claes",
    "size": 2
  },
  {
    "text": "team",
    "size": 2
  },
  {
    "text": "pro",
    "size": 2
  },
  {
    "text": "technologies",
    "size": 2
  },
  {
    "text": "lifting",
    "size": 2
  },
  {
    "text": "funky",
    "size": 2
  },
  {
    "text": "q-lite",
    "size": 2
  },
  {
    "text": "klussen",
    "size": 2
  },
  {
    "text": "roels",
    "size": 2
  },
  {
    "text": "solar",
    "size": 2
  },
  {
    "text": "consult",
    "size": 2
  },
  {
    "text": "depannage",
    "size": 2
  },
  {
    "text": "trans",
    "size": 2
  },
  {
    "text": "broeders",
    "size": 2
  },
  {
    "text": "peter",
    "size": 2
  },
  {
    "text": "richard",
    "size": 2
  },
  {
    "text": "print",
    "size": 2
  },
  {
    "text": "optiek",
    "size": 2
  },
  {
    "text": "alexandre",
    "size": 2
  },
  {
    "text": "schepper",
    "size": 2
  },
  {
    "text": "ruben",
    "size": 2
  },
  {
    "text": "supplies",
    "size": 2
  },
  {
    "text": "hoof",
    "size": 2
  },
  {
    "text": "machinery",
    "size": 2
  },
  {
    "text": "robert",
    "size": 2
  },
  {
    "text": "steve",
    "size": 2
  },
  {
    "text": "baert",
    "size": 2
  },
  {
    "text": "international",
    "size": 2
  },
  {
    "text": "wyckmans",
    "size": 2
  },
  {
    "text": "bert",
    "size": 2
  },
  {
    "text": "sander",
    "size": 2
  },
  {
    "text": "pieter",
    "size": 2
  },
  {
    "text": "global",
    "size": 2
  },
  {
    "text": "lieven",
    "size": 2
  },
  {
    "text": "belgie",
    "size": 2
  },
  {
    "text": "belgique",
    "size": 2
  },
  {
    "text": "invest",
    "size": 2
  },
  {
    "text": "jean",
    "size": 2
  },
  {
    "text": "jean-luc",
    "size": 2
  },
  {
    "text": "wooxi",
    "size": 2
  },
  {
    "text": "games",
    "size": 2
  },
  {
    "text": "vermeiren",
    "size": 2
  },
  {
    "text": "impala",
    "size": 2
  },
  {
    "text": "pascal",
    "size": 2
  },
  {
    "text": "vds",
    "size": 2
  },
  {
    "text": "hydraulics",
    "size": 2
  },
  {
    "text": "herstellingen",
    "size": 2
  },
  {
    "text": "belgië",
    "size": 2
  },
  {
    "text": "stijn",
    "size": 2
  },
  {
    "text": "verbist",
    "size": 2
  },
  {
    "text": "raf",
    "size": 2
  },
  {
    "text": "pool",
    "size": 2
  },
  {
    "text": "yvan",
    "size": 2
  },
  {
    "text": "kunstsmid",
    "size": 2
  },
  {
    "text": "damme",
    "size": 2
  },
  {
    "text": "act",
    "size": 2
  },
  {
    "text": "quentin",
    "size": 2
  },
  {
    "text": "vermander",
    "size": 2
  },
  {
    "text": "allround",
    "size": 2
  },
  {
    "text": "benjamin",
    "size": 2
  },
  {
    "text": "rico",
    "size": 2
  },
  {
    "text": "ahs",
    "size": 2
  },
  {
    "text": "reyniers",
    "size": 2
  },
  {
    "text": "system",
    "size": 2
  },
  {
    "text": "vsb",
    "size": 2
  },
  {
    "text": "medrott",
    "size": 2
  },
  {
    "text": "damien",
    "size": 2
  },
  {
    "text": "ets",
    "size": 2
  },
  {
    "text": "construction",
    "size": 2
  },
  {
    "text": "gambling",
    "size": 2
  },
  {
    "text": "filpro",
    "size": 2
  },
  {
    "text": "christiaan",
    "size": 2
  },
  {
    "text": "bonte",
    "size": 2
  },
  {
    "text": "janssens",
    "size": 2
  },
  {
    "text": "partners",
    "size": 2
  },
  {
    "text": "bonne",
    "size": 2
  },
  {
    "text": "jonathan",
    "size": 2
  },
  {
    "text": "instruments",
    "size": 2
  },
  {
    "text": "cars",
    "size": 2
  },
  {
    "text": "renovations",
    "size": 2
  },
  {
    "text": "bouw",
    "size": 2
  },
  {
    "text": "visie",
    "size": 2
  },
  {
    "text": "market",
    "size": 2
  },
  {
    "text": "andre",
    "size": 2
  },
  {
    "text": "david",
    "size": 2
  },
  {
    "text": "ludo",
    "size": 2
  },
  {
    "text": "bs",
    "size": 2
  },
  {
    "text": "seghers",
    "size": 2
  },
  {
    "text": "energie",
    "size": 2
  },
  {
    "text": "slotenmakerij",
    "size": 2
  },
  {
    "text": "mechanical",
    "size": 2
  },
  {
    "text": "hv",
    "size": 2
  },
  {
    "text": "it",
    "size": 2
  },
  {
    "text": "vintage",
    "size": 2
  },
  {
    "text": "works",
    "size": 2
  },
  {
    "text": "jv",
    "size": 2
  },
  {
    "text": "kortrijk",
    "size": 2
  },
  {
    "text": "eddy",
    "size": 2
  },
  {
    "text": "sergiu",
    "size": 2
  },
  {
    "text": "bma",
    "size": 2
  },
  {
    "text": "enterprises",
    "size": 2
  },
  {
    "text": "benoit",
    "size": 2
  },
  {
    "text": "jeroen",
    "size": 2
  },
  {
    "text": "contractors",
    "size": 2
  },
  {
    "text": "leuven",
    "size": 2
  },
  {
    "text": "yachting",
    "size": 2
  },
  {
    "text": "gybels",
    "size": 2
  },
  {
    "text": "one",
    "size": 2
  },
  {
    "text": "vl",
    "size": 2
  },
  {
    "text": "pure",
    "size": 2
  },
  {
    "text": "life",
    "size": 2
  },
  {
    "text": "creations",
    "size": 2
  },
  {
    "text": "pirtek",
    "size": 2
  },
  {
    "text": "gcv",
    "size": 2
  },
  {
    "text": "cooling",
    "size": 2
  },
  {
    "text": "sanitair",
    "size": 2
  },
  {
    "text": "distribution",
    "size": 2
  },
  {
    "text": "xavier",
    "size": 2
  },
  {
    "text": "power",
    "size": 2
  },
  {
    "text": "sound",
    "size": 2
  },
  {
    "text": "roel",
    "size": 2
  },
  {
    "text": "jonas",
    "size": 2
  },
  {
    "text": "belisa",
    "size": 2
  },
  {
    "text": "joris",
    "size": 2
  },
  {
    "text": "cleaning",
    "size": 2
  },
  {
    "text": "factory",
    "size": 2
  },
  {
    "text": "piping",
    "size": 2
  },
  {
    "text": "nove",
    "size": 1
  },
  {
    "text": "tdt",
    "size": 1
  },
  {
    "text": "gojy",
    "size": 1
  },
  {
    "text": "younessat",
    "size": 1
  },
  {
    "text": "datalink",
    "size": 1
  },
  {
    "text": "bering",
    "size": 1
  },
  {
    "text": "vvsnv",
    "size": 1
  },
  {
    "text": "coninx",
    "size": 1
  }
]