[
  {
    "text": "pharmacie",
    "size": 32,
    "category": "ander"
  },
  {
    "text": "medical",
    "size": 19,
    "category": "ander"
  },
  {
    "text": "bvba",
    "size": 14,
    "category": "rechtsvorm"
  },
  {
    "text": "belgium",
    "size": 12,
    "category": "land"
  },
  {
    "text": "care",
    "size": 11,
    "category": "ander"
  },
  {
    "text": "apotheek",
    "size": 10,
    "category": "ander"
  },
  {
    "text": "lease",
    "size": 8,
    "category": "ander"
  },
  {
    "text": "services",
    "size": 8,
    "category": "ander"
  },
  {
    "text": "hoorcentrum",
    "size": 7,
    "category": "ander"
  },
  {
    "text": "consult",
    "size": 7,
    "category": "ander"
  },
  {
    "text": "mediotheek",
    "size": 6,
    "category": "ander"
  },
  {
    "text": "thuisverpleging",
    "size": 6,
    "category": "ander"
  },
  {
    "text": "qualias",
    "size": 5,
    "category": "ander"
  },
  {
    "text": "sprl",
    "size": 5,
    "category": "rechtsvorm"
  },
  {
    "text": "soins",
    "size": 5,
    "category": "ander"
  },
  {
    "text": "centre",
    "size": 5,
    "category": "ander"
  },
  {
    "text": "group",
    "size": 5,
    "category": "ander"
  },
  {
    "text": "uitleendienst",
    "size": 5,
    "category": "ander"
  },
  {
    "text": "centrum",
    "size": 4,
    "category": "ander"
  },
  {
    "text": "vof",
    "size": 4,
    "category": "rechtsvorm"
  },
  {
    "text": "service",
    "size": 4,
    "category": "ander"
  },
  {
    "text": "and",
    "size": 4,
    "category": "ander"
  },
  {
    "text": "vzw",
    "size": 4,
    "category": "rechtsvorm"
  },
  {
    "text": "mobility",
    "size": 4,
    "category": "ander"
  },
  {
    "text": "orthopédie",
    "size": 4,
    "category": "ander"
  },
  {
    "text": "kine",
    "size": 4,
    "category": "ander"
  },
  {
    "text": "point",
    "size": 4,
    "category": "ander"
  },
  {
    "text": "dental",
    "size": 4,
    "category": "ander"
  },
  {
    "text": "company",
    "size": 4,
    "category": "ander"
  },
  {
    "text": "international",
    "size": 4,
    "category": "ander"
  },
  {
    "text": "vivantia",
    "size": 4,
    "category": "ander"
  },
  {
    "text": "pharma",
    "size": 4,
    "category": "ander"
  },
  {
    "text": "thuiszorgwinkel",
    "size": 4,
    "category": "ander"
  },
  {
    "text": "devices",
    "size": 3,
    "category": "ander"
  },
  {
    "text": "audition",
    "size": 3,
    "category": "ander"
  },
  {
    "text": "the",
    "size": 3,
    "category": "voornaam"
  },
  {
    "text": "healthcare",
    "size": 3,
    "category": "ander"
  },
  {
    "text": "fitclass",
    "size": 3,
    "category": "ander"
  },
  {
    "text": "design",
    "size": 3,
    "category": "ander"
  },
  {
    "text": "dokter",
    "size": 3,
    "category": "ander"
  },
  {
    "text": "vendor",
    "size": 3,
    "category": "ander"
  },
  {
    "text": "bernard",
    "size": 3,
    "category": "voornaam man"
  },
  {
    "text": "martine",
    "size": 3,
    "category": "voornaam vrouw"
  },
  {
    "text": "optique",
    "size": 3,
    "category": "ander"
  },
  {
    "text": "jasper",
    "size": 3,
    "category": "voornaam man"
  },
  {
    "text": "clinic",
    "size": 3,
    "category": "ander"
  },
  {
    "text": "santé",
    "size": 3,
    "category": "ander"
  },
  {
    "text": "co",
    "size": 3,
    "category": "ander"
  },
  {
    "text": "dr",
    "size": 3,
    "category": "ander"
  },
  {
    "text": "mire",
    "size": 3,
    "category": "voornaam vrouw"
  },
  {
    "text": "trading",
    "size": 3,
    "category": "ander"
  },
  {
    "text": "level",
    "size": 3,
    "category": "ander"
  },
  {
    "text": "ortho",
    "size": 3,
    "category": "ander"
  },
  {
    "text": "kbc",
    "size": 3,
    "category": "ander"
  },
  {
    "text": "assist",
    "size": 3,
    "category": "ander"
  },
  {
    "text": "invest",
    "size": 3,
    "category": "ander"
  },
  {
    "text": "solutions",
    "size": 3,
    "category": "ander"
  },
  {
    "text": "bandagisterie",
    "size": 3,
    "category": "ander"
  },
  {
    "text": "support",
    "size": 3,
    "category": "ander"
  },
  {
    "text": "europe",
    "size": 3,
    "category": "ander"
  },
  {
    "text": "cbc",
    "size": 3,
    "category": "ander"
  },
  {
    "text": "investment",
    "size": 2,
    "category": "ander"
  },
  {
    "text": "hendrickx",
    "size": 2,
    "category": "ander"
  },
  {
    "text": "medispa",
    "size": 2,
    "category": "ander"
  },
  {
    "text": "standard",
    "size": 2,
    "category": "ander"
  },
  {
    "text": "act",
    "size": 2,
    "category": "ander"
  },
  {
    "text": "fitness",
    "size": 2,
    "category": "ander"
  },
  {
    "text": "laser",
    "size": 2,
    "category": "ander"
  },
  {
    "text": "mobile",
    "size": 2,
    "category": "ander"
  },
  {
    "text": "with",
    "size": 2,
    "category": "ander"
  },
  {
    "text": "spirit",
    "size": 2,
    "category": "ander"
  },
  {
    "text": "groep",
    "size": 2,
    "category": "ander"
  },
  {
    "text": "medic",
    "size": 2,
    "category": "ander"
  },
  {
    "text": "immo",
    "size": 2,
    "category": "ander"
  },
  {
    "text": "landen",
    "size": 2,
    "category": "ander"
  },
  {
    "text": "consulting",
    "size": 2,
    "category": "ander"
  },
  {
    "text": "medica",
    "size": 2,
    "category": "ander"
  },
  {
    "text": "anne",
    "size": 2,
    "category": "voornaam"
  },
  {
    "text": "school",
    "size": 2,
    "category": "ander"
  },
  {
    "text": "tech",
    "size": 2,
    "category": "ander"
  },
  {
    "text": "engineering",
    "size": 2,
    "category": "ander"
  },
  {
    "text": "shop",
    "size": 2,
    "category": "ander"
  },
  {
    "text": "center",
    "size": 2,
    "category": "ander"
  },
  {
    "text": "centea",
    "size": 2,
    "category": "ander"
  },
  {
    "text": "moyson",
    "size": 2,
    "category": "ander"
  },
  {
    "text": "elite",
    "size": 2,
    "category": "ander"
  },
  {
    "text": "logistics",
    "size": 2,
    "category": "ander"
  },
  {
    "text": "park",
    "size": 2,
    "category": "ander"
  },
  {
    "text": "dedobbeleer",
    "size": 2,
    "category": "ander"
  },
  {
    "text": "entreprise",
    "size": 2,
    "category": "ander"
  },
  {
    "text": "steven",
    "size": 2,
    "category": "voornaam man"
  },
  {
    "text": "zorgpunt",
    "size": 2,
    "category": "ander"
  },
  {
    "text": "be",
    "size": 2,
    "category": "ander"
  },
  {
    "text": "bv",
    "size": 2,
    "category": "rechtsvorm"
  },
  {
    "text": "food",
    "size": 2,
    "category": "ander"
  },
  {
    "text": "beauty",
    "size": 2,
    "category": "voornaam vrouw"
  },
  {
    "text": "michel",
    "size": 2,
    "category": "voornaam"
  },
  {
    "text": "dillen",
    "size": 2,
    "category": "voornaam man"
  },
  {
    "text": "vision",
    "size": 2,
    "category": "ander"
  },
  {
    "text": "immolease",
    "size": 2,
    "category": "ander"
  },
  {
    "text": "alpha",
    "size": 2,
    "category": "voornaam"
  },
  {
    "text": "toque",
    "size": 2,
    "category": "ander"
  },
  {
    "text": "management",
    "size": 2,
    "category": "ander"
  },
  {
    "text": "diving",
    "size": 2,
    "category": "ander"
  },
  {
    "text": "brasseur",
    "size": 2,
    "category": "ander"
  },
  {
    "text": "tandartsenpraktijk",
    "size": 2,
    "category": "ander"
  },
  {
    "text": "health",
    "size": 2,
    "category": "ander"
  },
  {
    "text": "philippe",
    "size": 2,
    "category": "voornaam man"
  },
  {
    "text": "plus",
    "size": 2,
    "category": "ander"
  },
  {
    "text": "groepspraktijk",
    "size": 2,
    "category": "ander"
  },
  {
    "text": "hove",
    "size": 2,
    "category": "ander"
  },
  {
    "text": "nv",
    "size": 2,
    "category": "rechtsvorm"
  },
  {
    "text": "confort",
    "size": 2,
    "category": "ander"
  },
  {
    "text": "désirs",
    "size": 2,
    "category": "ander"
  },
  {
    "text": "global",
    "size": 2,
    "category": "ander"
  },
  {
    "text": "qrs",
    "size": 2,
    "category": "ander"
  },
  {
    "text": "sofie",
    "size": 2,
    "category": "voornaam vrouw"
  },
  {
    "text": "assistance",
    "size": 2,
    "category": "ander"
  },
  {
    "text": "life",
    "size": 2,
    "category": "ander"
  },
  {
    "text": "thuiszorgshop",
    "size": 2,
    "category": "ander"
  },
  {
    "text": "keshe",
    "size": 2,
    "category": "ander"
  },
  {
    "text": "foundation",
    "size": 2,
    "category": "ander"
  },
  {
    "text": "christophe",
    "size": 2,
    "category": "voornaam man"
  },
  {
    "text": "first",
    "size": 2,
    "category": "ander"
  },
  {
    "text": "leasing",
    "size": 2,
    "category": "ander"
  },
  {
    "text": "holding",
    "size": 2,
    "category": "ander"
  },
  {
    "text": "talma",
    "size": 2,
    "category": "ander"
  },
  {
    "text": "l\u0027eden",
    "size": 2,
    "category": "ander"
  },
  {
    "text": "triomed",
    "size": 2,
    "category": "ander"
  },
  {
    "text": "medeor",
    "size": 1,
    "category": "ander"
  },
  {
    "text": "airpec",
    "size": 1,
    "category": "ander"
  },
  {
    "text": "lexmedical",
    "size": 1,
    "category": "ander"
  },
  {
    "text": "acoba",
    "size": 1,
    "category": "ander"
  },
  {
    "text": "heideveld",
    "size": 1,
    "category": "ander"
  },
  {
    "text": "ego",
    "size": 1,
    "category": "ander"
  },
  {
    "text": "pierre",
    "size": 1,
    "category": "voornaam"
  },
  {
    "text": "via",
    "size": 1,
    "category": "ander"
  },
  {
    "text": "high-tech",
    "size": 1,
    "category": "ander"
  },
  {
    "text": "vie",
    "size": 1,
    "category": "voornaam vrouw"
  },
  {
    "text": "orthopedie",
    "size": 1,
    "category": "ander"
  },
  {
    "text": "mestag",
    "size": 1,
    "category": "ander"
  },
  {
    "text": "alcyon",
    "size": 1,
    "category": "ander"
  },
  {
    "text": "sinustec",
    "size": 1,
    "category": "ander"
  },
  {
    "text": "connexcity",
    "size": 1,
    "category": "ander"
  },
  {
    "text": "airport",
    "size": 1,
    "category": "ander"
  },
  {
    "text": "medi-point",
    "size": 1,
    "category": "ander"
  },
  {
    "text": "planning",
    "size": 1,
    "category": "ander"
  },
  {
    "text": "magusta",
    "size": 1,
    "category": "ander"
  },
  {
    "text": "haarstudio",
    "size": 1,
    "category": "ander"
  },
  {
    "text": "synapses",
    "size": 1,
    "category": "ander"
  },
  {
    "text": "stop",
    "size": 1,
    "category": "ander"
  },
  {
    "text": "gomedis",
    "size": 1,
    "category": "ander"
  },
  {
    "text": "tamines",
    "size": 1,
    "category": "ander"
  },
  {
    "text": "corveleyn",
    "size": 1,
    "category": "ander"
  },
  {
    "text": "myny",
    "size": 1,
    "category": "ander"
  },
  {
    "text": "home-care",
    "size": 1,
    "category": "ander"
  },
  {
    "text": "herzet",
    "size": 1,
    "category": "ander"
  },
  {
    "text": "vande",
    "size": 1,
    "category": "ander"
  },
  {
    "text": "luminenca",
    "size": 1,
    "category": "ander"
  },
  {
    "text": "isurgic",
    "size": 1,
    "category": "ander"
  },
  {
    "text": "magazijn",
    "size": 1,
    "category": "ander"
  },
  {
    "text": "liégeois",
    "size": 1,
    "category": "ander"
  },
  {
    "text": "gold",
    "size": 1,
    "category": "ander"
  },
  {
    "text": "everseen",
    "size": 1,
    "category": "ander"
  },
  {
    "text": "hannecart",
    "size": 1,
    "category": "ander"
  },
  {
    "text": "medicaspec",
    "size": 1,
    "category": "ander"
  },
  {
    "text": "cima",
    "size": 1,
    "category": "ander"
  },
  {
    "text": "wunjo",
    "size": 1,
    "category": "ander"
  },
  {
    "text": "rentys",
    "size": 1,
    "category": "ander"
  },
  {
    "text": "medicotheek",
    "size": 1,
    "category": "ander"
  },
  {
    "text": "samm",
    "size": 1,
    "category": "ander"
  },
  {
    "text": "orthofin",
    "size": 1,
    "category": "ander"
  },
  {
    "text": "kaland",
    "size": 1,
    "category": "ander"
  },
  {
    "text": "ergomed",
    "size": 1,
    "category": "ander"
  },
  {
    "text": "femme",
    "size": 1,
    "category": "voornaam vrouw"
  },
  {
    "text": "labophar",
    "size": 1,
    "category": "ander"
  },
  {
    "text": "sitwear",
    "size": 1,
    "category": "ander"
  },
  {
    "text": "opticura",
    "size": 1,
    "category": "ander"
  },
  {
    "text": "blue",
    "size": 1,
    "category": "voornaam vrouw"
  },
  {
    "text": "marjan",
    "size": 1,
    "category": "voornaam"
  },
  {
    "text": "pharmabouge",
    "size": 1,
    "category": "ander"
  },
  {
    "text": "abw",
    "size": 1,
    "category": "ander"
  },
  {
    "text": "knauf",
    "size": 1,
    "category": "ander"
  },
  {
    "text": "mello",
    "size": 1,
    "category": "ander"
  },
  {
    "text": "plumen",
    "size": 1,
    "category": "ander"
  },
  {
    "text": "aerospace",
    "size": 1,
    "category": "ander"
  },
  {
    "text": "vacu-move",
    "size": 1,
    "category": "ander"
  },
  {
    "text": "plasma",
    "size": 1,
    "category": "ander"
  },
  {
    "text": "facet",
    "size": 1,
    "category": "ander"
  },
  {
    "text": "surgery",
    "size": 1,
    "category": "ander"
  },
  {
    "text": "wheels",
    "size": 1,
    "category": "ander"
  },
  {
    "text": "infraligna",
    "size": 1,
    "category": "ander"
  },
  {
    "text": "instrumen",
    "size": 1,
    "category": "ander"
  },
  {
    "text": "sinico",
    "size": 1,
    "category": "ander"
  },
  {
    "text": "acm",
    "size": 1,
    "category": "ander"
  },
  {
    "text": "stroobants",
    "size": 1,
    "category": "ander"
  },
  {
    "text": "red",
    "size": 1,
    "category": "ander"
  },
  {
    "text": "supp-ortho",
    "size": 1,
    "category": "ander"
  },
  {
    "text": "zorgexpo",
    "size": 1,
    "category": "ander"
  },
  {
    "text": "gezondheidswinkel",
    "size": 1,
    "category": "ander"
  },
  {
    "text": "controle",
    "size": 1,
    "category": "ander"
  },
  {
    "text": "export",
    "size": 1,
    "category": "ander"
  },
  {
    "text": "crisnée",
    "size": 1,
    "category": "ander"
  },
  {
    "text": "haromed",
    "size": 1,
    "category": "ander"
  },
  {
    "text": "innoser",
    "size": 1,
    "category": "ander"
  },
  {
    "text": "matthias",
    "size": 1,
    "category": "voornaam man"
  },
  {
    "text": "clinique",
    "size": 1,
    "category": "ander"
  },
  {
    "text": "orto-advance",
    "size": 1,
    "category": "ander"
  },
  {
    "text": "belgique-luxembourg",
    "size": 1,
    "category": "ander"
  },
  {
    "text": "els",
    "size": 1,
    "category": "voornaam vrouw"
  },
  {
    "text": "verstraete",
    "size": 1,
    "category": "ander"
  },
  {
    "text": "heartaedlife",
    "size": 1,
    "category": "ander"
  },
  {
    "text": "yves",
    "size": 1,
    "category": "voornaam man"
  },
  {
    "text": "labs",
    "size": 1,
    "category": "ander"
  },
  {
    "text": "braems",
    "size": 1,
    "category": "ander"
  },
  {
    "text": "lückerath",
    "size": 1,
    "category": "ander"
  },
  {
    "text": "technics",
    "size": 1,
    "category": "ander"
  },
  {
    "text": "cie",
    "size": 1,
    "category": "ander"
  },
  {
    "text": "cg\u0027s",
    "size": 1,
    "category": "ander"
  },
  {
    "text": "trust",
    "size": 1,
    "category": "ander"
  },
  {
    "text": "oud-heverlee",
    "size": 1,
    "category": "ander"
  },
  {
    "text": "production",
    "size": 1,
    "category": "ander"
  },
  {
    "text": "bollybot",
    "size": 1,
    "category": "ander"
  },
  {
    "text": "delphine",
    "size": 1,
    "category": "voornaam vrouw"
  },
  {
    "text": "medicalis",
    "size": 1,
    "category": "ander"
  },
  {
    "text": "jette",
    "size": 1,
    "category": "voornaam vrouw"
  },
  {
    "text": "emv",
    "size": 1,
    "category": "ander"
  },
  {
    "text": "oude",
    "size": 1,
    "category": "ander"
  },
  {
    "text": "gewrichtskliniek",
    "size": 1,
    "category": "ander"
  },
  {
    "text": "timsonet",
    "size": 1,
    "category": "ander"
  },
  {
    "text": "wallogistic",
    "size": 1,
    "category": "ander"
  },
  {
    "text": "patrick",
    "size": 1,
    "category": "voornaam man"
  },
  {
    "text": "biotandarts",
    "size": 1,
    "category": "ander"
  },
  {
    "text": "mobiliteit",
    "size": 1,
    "category": "ander"
  },
  {
    "text": "bulles",
    "size": 1,
    "category": "ander"
  },
  {
    "text": "pauquay",
    "size": 1,
    "category": "ander"
  },
  {
    "text": "powercare-powerstage",
    "size": 1,
    "category": "ander"
  },
  {
    "text": "vandermeersch",
    "size": 1,
    "category": "ander"
  },
  {
    "text": "iyengar",
    "size": 1,
    "category": "ander"
  },
  {
    "text": "cvim",
    "size": 1,
    "category": "ander"
  },
  {
    "text": "scts",
    "size": 1,
    "category": "ander"
  },
  {
    "text": "verhagen",
    "size": 1,
    "category": "ander"
  },
  {
    "text": "bangagisterie",
    "size": 1,
    "category": "ander"
  },
  {
    "text": "lema",
    "size": 1,
    "category": "voornaam"
  },
  {
    "text": "mod\u0027in",
    "size": 1,
    "category": "ander"
  },
  {
    "text": "gsn",
    "size": 1,
    "category": "ander"
  },
  {
    "text": "leenders",
    "size": 1,
    "category": "ander"
  },
  {
    "text": "imagerie",
    "size": 1,
    "category": "ander"
  },
  {
    "text": "denoyel",
    "size": 1,
    "category": "ander"
  },
  {
    "text": "med-art",
    "size": 1,
    "category": "ander"
  }
]